ancb/__init__.py
ancb-0.1.2.dist-info/LICENSE
ancb-0.1.2.dist-info/METADATA
ancb-0.1.2.dist-info/WHEEL
ancb-0.1.2.dist-info/RECORD
