Metadata-Version: 2.1
Name: ancb
Version: 0.1.2
Summary: Fast, efficient, and powerful NumPy compatible circular buffers.
Home-page: https://github.com/EmDash00/ANCB
License: Apache-2.0
Author: Ember Chow
Author-email: emberchow.business@gmail.com
Requires-Python: >=3.6,<4.0
Classifier: License :: OSI Approved :: Apache Software License
Classifier: Operating System :: OS Independent
Classifier: Programming Language :: Python :: 3
Classifier: Programming Language :: Python :: 3.6
Classifier: Programming Language :: Python :: 3.7
Classifier: Programming Language :: Python :: 3.8
Classifier: Programming Language :: Python :: 3.9
Classifier: Programming Language :: Python :: 3.10
Classifier: Programming Language :: Python :: 3.11
Classifier: Programming Language :: Python :: 3.12
Requires-Dist: numpy (>=1.16.4,<2.0.0) ; python_version >= "3.6"
Requires-Dist: numpy (>=1.20.0,<2.0.0) ; python_version >= "3.8" and python_version < "3.12"
Requires-Dist: numpy (>=1.26.0,<2.0.0) ; python_version >= "3.12" and python_version < "3.13"
Project-URL: Documentation, https://ancb-docs.readthedocs.io/en/latest/
Project-URL: Repository, https://github.com/EmDash00/ANCB
